reposort/__init__.py
reposort/__main__.py
reposort/cli.py
reposort/core.py
reposort-3.1.1.dist-info/METADATA
reposort-3.1.1.dist-info/WHEEL
reposort-3.1.1.dist-info/entry_points.txt
reposort-3.1.1.dist-info/licenses/LICENSE
reposort-3.1.1.dist-info/RECORD
