Metadata-Version: 2.4
Name: reposort
Version: 3.1.1
Summary: Organize git repositories by their origin URL
Author-email: thys <sthysel@gmail.com>
License-File: LICENSE
Requires-Python: >=3.13
Requires-Dist: click>=8.1.7
Requires-Dist: rich>=14.0.0
